aio_throttle/__init__.py
aio_throttle/aiohttp.py
aio_throttle/base.py
aio_throttle/internals.py
aio_throttle/metrics.py
aio_throttle/prometheus.py
aio_throttle/py.typed
aio_throttle/quotas.py
aio_throttle/throttle.py
aio_throttle/utils.py
aio_throttle-1.7.0.dist-info/LICENSE
aio_throttle-1.7.0.dist-info/METADATA
aio_throttle-1.7.0.dist-info/WHEEL
aio_throttle-1.7.0.dist-info/top_level.txt
aio_throttle-1.7.0.dist-info/RECORD
