Metadata-Version: 2.1
Name: aio-throttle
Version: 1.7.0
Summary: A simple throttling package
Home-page: https://github.com/Pliner/aio-throttle
Author: Yury Pliner
Author-email: yury.pliner@gmail.com
License: UNKNOWN
Platform: UNKNOWN
Requires-Python: >=3.7
License-File: LICENSE
